[
  {
    "id": "perlato-45",
    "title": "Гель-лак Perlato #45",
    "subtitle": "Графит",
    "category": "gel-lak",
    "sku": "PRL-45",
    "volume": "10 мл",
    "price": 690,
    "price_old": null,
    "description": "Перламутровый графитовый оттенок с холодным подтоном. Однослойное покрытие, плотная пигментация.",
    "in_stock": true,
    "photos": [],
    "videos": [],
    "hero_video": null,
    "tags": [
      "bestseller"
    ],
    "sort_order": 10
  },
  {
    "id": "butterfly-set",
    "title": "Набор для дизайна «Бабочка»",
    "subtitle": "С блёстками и фольгой",
    "category": "decor",
    "sku": "BTF-01",
    "volume": null,
    "price": 1250,
    "price_old": null,
    "description": "Набор для создания эффекта «Butterfly Wings». Содержит блёстки, фольгу, кисть.",
    "in_stock": true,
    "photos": [],
    "videos": [],
    "hero_video": null,
    "tags": [
      "new"
    ],
    "sort_order": 20
  },
  {
    "id": "basetop",
    "title": "База + Топ перламутровый",
    "subtitle": "Комплект",
    "category": "gels",
    "sku": "BTP-01",
    "volume": "10+10 мл",
    "price": 700,
    "price_old": null,
    "description": "База с эффектом мерцания и финишный топ без липкого слоя.",
    "in_stock": true,
    "photos": [],
    "videos": [],
    "hero_video": null,
    "tags": [],
    "sort_order": 30
  },
  {
    "id": "uv-lamp",
    "title": "УФ-лампа 36W",
    "subtitle": "С таймером",
    "category": "equipment",
    "sku": "LMP-36",
    "volume": null,
    "price": 2990,
    "price_old": null,
    "description": "УФ/LED лампа 36W с таймером 30/60/90 сек, режим непрерывной работы.",
    "in_stock": true,
    "photos": [],
    "videos": [],
    "hero_video": null,
    "tags": [
      "bestseller"
    ],
    "sort_order": 40
  },
  {
    "id": "rollback-test-v2",
    "title": "V2 ROLLBACK TEST",
    "category": "gels",
    "price": 2,
    "subtitle": "",
    "sku": null,
    "volume": null,
    "price_old": null,
    "description": "",
    "in_stock": true,
    "photos": [],
    "videos": [],
    "hero_video": null,
    "tags": [],
    "sort_order": 999
  }
]